AUTHORS
LICENSE
MANIFEST.in
README
setup.py
stringslipper.py
stringslipper.egg-info/PKG-INFO
stringslipper.egg-info/SOURCES.txt
stringslipper.egg-info/dependency_links.txt
stringslipper.egg-info/top_level.txt