Metadata-Version: 1.0
Name: stringslipper
Version: 0.1.2
Summary: Quicksilver-like pattern matching
Home-page: http://github.com/gorakhargosh/stringslipper
Author: Gora Khargosh
Author-email: gora.khargosh@gmail.com
License: MIT License
Platform: UNKNOWN
Classifier: Development Status :: 3 - Alpha
Classifier: Intended Audience :: Developers
Classifier: License :: OSI Approved :: MIT License
Classifier: Natural Language :: English
Classifier: Operating System :: OS Independent
Classifier: Programming Language :: Python
Classifier: Topic :: Software Development :: Libraries
Classifier: Topic :: Utilities
